aurane/__init__.py
aurane/ast.py
aurane/cli.py
aurane/cli_enhanced.py
aurane/codegen_torch.py
aurane/compiler.py
aurane/optimizer.py
aurane/parser.py
aurane/profiler.py
aurane/semantic_analyzer.py
aurane/type_checker.py
aurane/visualizer.py
aurane-0.1.0.dist-info/METADATA
aurane-0.1.0.dist-info/WHEEL
aurane-0.1.0.dist-info/entry_points.txt
aurane-0.1.0.dist-info/top_level.txt
aurane-0.1.0.dist-info/RECORD
