Metadata-Version: 2.4
Name: aurane
Version: 0.1.0
Summary: A modern domain-specific language for machine learning that compiles to PyTorch
Author: Desenyon
License-Expression: MIT
Project-URL: Homepage, https://github.com/desenyon/aurane
Project-URL: Repository, https://github.com/desenyon/aurane
Keywords: ml,dsl,pytorch,transpiler,machine-learning,deep-learning,neural-networks
Classifier: Development Status :: 4 - Beta
Classifier: Intended Audience :: Developers
Classifier: Intended Audience :: Science/Research
Classifier: Programming Language :: Python :: 3
Classifier: Programming Language :: Python :: 3.10
Classifier: Programming Language :: Python :: 3.11
Classifier: Programming Language :: Python :: 3.12
Classifier: Topic :: Scientific/Engineering :: Artificial Intelligence
Classifier: Topic :: Software Development :: Compilers
Classifier: Topic :: Software Development :: Code Generators
Requires-Python: >=3.10
Requires-Dist: rich>=13.0.0
Requires-Dist: click>=8.0.0
Requires-Dist: pyyaml>=6.0.0
Requires-Dist: watchdog>=3.0.0
Provides-Extra: torch
Requires-Dist: torch>=2.0.0; extra == "torch"
Requires-Dist: torchvision>=0.15.0; extra == "torch"
Requires-Dist: matplotlib>=3.5.0; extra == "torch"
Requires-Dist: tensorboard>=2.11.0; extra == "torch"
Provides-Extra: dev
Requires-Dist: pytest>=7.0.0; extra == "dev"
Requires-Dist: black>=23.0.0; extra == "dev"
Requires-Dist: mypy>=1.0.0; extra == "dev"
Provides-Extra: all
Requires-Dist: aurane[torch]; extra == "all"
